pibooth_picture_template.py
pibooth_picture_template-1.1.0.dist-info/LICENSE
pibooth_picture_template-1.1.0.dist-info/METADATA
pibooth_picture_template-1.1.0.dist-info/WHEEL
pibooth_picture_template-1.1.0.dist-info/entry_points.txt
pibooth_picture_template-1.1.0.dist-info/top_level.txt
pibooth_picture_template-1.1.0.dist-info/RECORD
