Metadata-Version: 2.1
Name: pibooth-picture-template
Version: 1.1.0
Summary: Pibooth plugin to customize the final picture layout using Flowchart Maker.
Home-page: https://github.com/pibooth/pibooth-picture-template
Author: Vincent Verdeil, Antoine Rousseaux
License: GPLv3
Download-URL: https://github.com/pibooth/pibooth-picture-template/archive/1.1.0.tar.gz
Keywords: Raspberry Pi,camera,photobooth
Platform: unix
Platform: linux
Classifier: Development Status :: 5 - Production/Stable
Classifier: Environment :: Other Environment
Classifier: Intended Audience :: Developers
Classifier: Intended Audience :: End Users/Desktop
Classifier: License :: OSI Approved :: GNU General Public License v3 or later (GPLv3+)
Classifier: Operating System :: POSIX :: Linux
Classifier: Programming Language :: Python :: 3.6
Classifier: Programming Language :: Python :: 3.7
Classifier: Programming Language :: Python :: 3.8
Classifier: Programming Language :: Python :: 3.9
Classifier: Natural Language :: English
Classifier: Topic :: Multimedia :: Graphics :: Capture :: Digital Camera
Requires-Python: >=3.6
License-File: LICENSE
Requires-Dist: pibooth (>=2.0.0)
